{
  "id": "lowluckstatgen-dnd5e",
  "title": "Low Luck Stat Generation for D&D 5e",
  "description": "Stat generation module for D&D 5e as described by Treantmonk here: https://www.youtube.com/watch?v=3SkT1MJ6im8",
  "author": "ddipaolo",
  "authors": [
    {
      "name": "ddipaolo"
    }
  ],
  "languages": [
    {
      "lang": "en",
      "name": "English",
      "path": "languages/en.json"
    }
  ],
  "esmodules": [ "scripts/module.js" ],
  "styles": [ "styles/module.css" ],
  "version": "1",
  "system": ["dnd5e"],
  "relationships": {
    "systems": [
      {
        "id": "dnd5e",
        "type": "system"
      }
    ]
  },
  "compatibility": {
    "minimum": 10,
    "verified": "10.288",
    "maximum": 10
  }
}
